<?xml version="1.0" encoding="UTF-8" standalone="yes"?>
<AWSDWModel>
    <id>obj_1598c7f5a83d4f63837378b3dff60b49</id>
    <createUser>admin</createUser>
    <createTime>2020-05-15 10:44:53</createTime>
    <updateUser></updateUser>
    <updateTime>2020-05-15 10:44:53</updateTime>
    <signature>tGOmxiTgjT/77UoYpSlq8Vc+hHPRoJWHdZexXc7zEpYuMNdhvSICeJnlc/RzRHGrnyfsXeKbzpGGAR9YYrgD1OAl/k2NlUwW1FSkNJ08zfkqcPjO+An3hFF7d4V2M3d2</signature>
    <managed>false</managed>
    <processGroupId>obj_1598c7f5a83d4f63837378b3dff60b49</processGroupId>
    <processGroupName>物业房产档案</processGroupName>
    <categoryName>未分类</categoryName>
    <dwType>1</dwType>
    <processAdministrator></processAdministrator>
    <title id="obj_9fbab9ea801c40839531fd3c492e912f" label="物业房产档案" extendcode="" event=""/>
    <userextendbuttons/>
    <userextendbehaviors/>
    <iconFontCode></iconFontCode>
    <iconFontColor></iconFontColor>
</AWSDWModel>
