<?xml version="1.0" encoding="UTF-8" standalone="yes"?>
<formModel>
    <id>d3ec61d5-ef7b-4901-8c91-bbf65cf08497</id>
    <createUser>admin</createUser>
    <createTime>2020-05-18 15:59:36</createTime>
    <updateUser></updateUser>
    <updateTime>2020-05-18 15:59:36</updateTime>
    <signature>tGOmxiTgjT/77UoYpSlq8Vc+hHPRoJWHdZexXc7zEpYuMNdhvSICeJnlc/RzRHGrzxmy77PqwnXIYLBNvbe5f/MrK/LZ6ZoiHzb4rJVqUo7m0zVZT6mqq4CIWTqIi2TR</signature>
    <managed>false</managed>
    <title>维修维保类型档案</title>
    <deleted>false</deleted>
    <categoryName>车辆管理</categoryName>
    <administrator>admin</administrator>
    <defaultLanguage></defaultLanguage>
    <url></url>
    <urlHeight></urlHeight>
    <formItems>
        <formItem>
            <id>2c22f7f4-bf17-44ce-aa67-3f41e2c647f2</id>
            <title>维修维保类型档案</title>
            <templateFile>{"tablet":"车辆管理-维修维保类型档案.htm","pc":"车辆管理-维修维保类型档案.htm","mobile":"车辆管理-维修维保类型档案_m.htm"}</templateFile>
            <grid>false</grid>
            <gridSetting></gridSetting>
            <orderBy></orderBy>
            <pageLimit>0</pageLimit>
            <boModelId>26bc875f-c7f3-473c-9dd8-b927097e510a</boModelId>
            <dictionaryFileName></dictionaryFileName>
            <hiddenHead>false</hiddenHead>
            <theme>{"pc":"_bpm.platform","mobile":"_bpm.platform"}</theme>
            <itemDisplays/>
            <scheme>{}</scheme>
            <calcFormula></calcFormula>
            <conditionControl></conditionControl>
            <validate></validate>
            <icon></icon>
            <gridControl></gridControl>
            <summaryControl></summaryControl>
            <ruleControl></ruleControl>
            <hiddenFields></hiddenFields>
            <hiddenAddBtn>false</hiddenAddBtn>
            <verticalLayout>false</verticalLayout>
        </formItem>
    </formItems>
</formModel>
